{
  "id": "4e354444-9646-49ad-983d-1ba3bee2c817",
  "prevId": "00000000-0000-0000-0000-000000000000",
  "version": "7",
  "dialect": "postgresql",
  "tables": {
    "public.activity_records": {
      "name": "activity_records",
      "schema": "",
      "columns": {
        "id": {
          "name": "id",
          "type": "uuid",
          "primaryKey": true,
          "notNull": true,
          "default": "gen_random_uuid()"
        },
        "pet_id": {
          "name": "pet_id",
          "type": "uuid",
          "primaryKey": false,
          "notNull": true
        },
        "date": {
          "name": "date",
          "type": "timestamp",
          "primaryKey": false,
          "notNull": true
        },
        "steps": {
          "name": "steps",
          "type": "integer",
          "primaryKey": false,
          "notNull": false,
          "default": 0
        },
        "active_minutes": {
          "name": "active_minutes",
          "type": "integer",
          "primaryKey": false,
          "notNull": false,
          "default": 0
        },
        "sleep_minutes": {
          "name": "sleep_minutes",
          "type": "integer",
          "primaryKey": false,
          "notNull": false,
          "default": 0
        },
        "calories": {
          "name": "calories",
          "type": "integer",
          "primaryKey": false,
          "notNull": false,
          "default": 0
        },
        "distance": {
          "name": "distance",
          "type": "numeric(8, 2)",
          "primaryKey": false,
          "notNull": false,
          "default": "'0'"
        },
        "activity_type": {
          "name": "activity_type",
          "type": "activity_type",
          "typeSchema": "public",
          "primaryKey": false,
          "notNull": false
        },
        "notes": {
          "name": "notes",
          "type": "text",
          "primaryKey": false,
          "notNull": false
        },
        "created_at": {
          "name": "created_at",
          "type": "timestamp",
          "primaryKey": false,
          "notNull": true,
          "default": "now()"
        },
        "updated_at": {
          "name": "updated_at",
          "type": "timestamp",
          "primaryKey": false,
          "notNull": true,
          "default": "now()"
        }
      },
      "indexes": {},
      "foreignKeys": {
        "activity_records_pet_id_pets_id_fk": {
          "name": "activity_records_pet_id_pets_id_fk",
          "tableFrom": "activity_records",
          "tableTo": "pets",
          "columnsFrom": [
            "pet_id"
          ],
          "columnsTo": [
            "id"
          ],
          "onDelete": "cascade",
          "onUpdate": "no action"
        }
      },
      "compositePrimaryKeys": {},
      "uniqueConstraints": {},
      "policies": {},
      "checkConstraints": {},
      "isRLSEnabled": false
    },
    "public.health_records": {
      "name": "health_records",
      "schema": "",
      "columns": {
        "id": {
          "name": "id",
          "type": "uuid",
          "primaryKey": true,
          "notNull": true,
          "default": "gen_random_uuid()"
        },
        "pet_id": {
          "name": "pet_id",
          "type": "uuid",
          "primaryKey": false,
          "notNull": true
        },
        "record_date": {
          "name": "record_date",
          "type": "timestamp",
          "primaryKey": false,
          "notNull": true
        },
        "temperature": {
          "name": "temperature",
          "type": "numeric(4, 1)",
          "primaryKey": false,
          "notNull": false
        },
        "heart_rate": {
          "name": "heart_rate",
          "type": "integer",
          "primaryKey": false,
          "notNull": false
        },
        "weight": {
          "name": "weight",
          "type": "numeric(5, 2)",
          "primaryKey": false,
          "notNull": false
        },
        "blood_pressure": {
          "name": "blood_pressure",
          "type": "text",
          "primaryKey": false,
          "notNull": false
        },
        "status": {
          "name": "status",
          "type": "health_status",
          "typeSchema": "public",
          "primaryKey": false,
          "notNull": true,
          "default": "'normal'"
        },
        "symptoms": {
          "name": "symptoms",
          "type": "text",
          "primaryKey": false,
          "notNull": false
        },
        "medications": {
          "name": "medications",
          "type": "jsonb",
          "primaryKey": false,
          "notNull": false
        },
        "vet_notes": {
          "name": "vet_notes",
          "type": "text",
          "primaryKey": false,
          "notNull": false
        },
        "next_checkup": {
          "name": "next_checkup",
          "type": "timestamp",
          "primaryKey": false,
          "notNull": false
        },
        "created_at": {
          "name": "created_at",
          "type": "timestamp",
          "primaryKey": false,
          "notNull": true,
          "default": "now()"
        },
        "updated_at": {
          "name": "updated_at",
          "type": "timestamp",
          "primaryKey": false,
          "notNull": true,
          "default": "now()"
        }
      },
      "indexes": {},
      "foreignKeys": {
        "health_records_pet_id_pets_id_fk": {
          "name": "health_records_pet_id_pets_id_fk",
          "tableFrom": "health_records",
          "tableTo": "pets",
          "columnsFrom": [
            "pet_id"
          ],
          "columnsTo": [
            "id"
          ],
          "onDelete": "cascade",
          "onUpdate": "no action"
        }
      },
      "compositePrimaryKeys": {},
      "uniqueConstraints": {},
      "policies": {},
      "checkConstraints": {},
      "isRLSEnabled": false
    },
    "public.location_records": {
      "name": "location_records",
      "schema": "",
      "columns": {
        "id": {
          "name": "id",
          "type": "uuid",
          "primaryKey": true,
          "notNull": true,
          "default": "gen_random_uuid()"
        },
        "pet_id": {
          "name": "pet_id",
          "type": "uuid",
          "primaryKey": false,
          "notNull": true
        },
        "latitude": {
          "name": "latitude",
          "type": "numeric(10, 8)",
          "primaryKey": false,
          "notNull": true
        },
        "longitude": {
          "name": "longitude",
          "type": "numeric(11, 8)",
          "primaryKey": false,
          "notNull": true
        },
        "altitude": {
          "name": "altitude",
          "type": "numeric(8, 2)",
          "primaryKey": false,
          "notNull": false
        },
        "accuracy": {
          "name": "accuracy",
          "type": "numeric(6, 2)",
          "primaryKey": false,
          "notNull": false
        },
        "address": {
          "name": "address",
          "type": "text",
          "primaryKey": false,
          "notNull": false
        },
        "place_name": {
          "name": "place_name",
          "type": "text",
          "primaryKey": false,
          "notNull": false
        },
        "recorded_at": {
          "name": "recorded_at",
          "type": "timestamp",
          "primaryKey": false,
          "notNull": true
        },
        "created_at": {
          "name": "created_at",
          "type": "timestamp",
          "primaryKey": false,
          "notNull": true,
          "default": "now()"
        }
      },
      "indexes": {},
      "foreignKeys": {
        "location_records_pet_id_pets_id_fk": {
          "name": "location_records_pet_id_pets_id_fk",
          "tableFrom": "location_records",
          "tableTo": "pets",
          "columnsFrom": [
            "pet_id"
          ],
          "columnsTo": [
            "id"
          ],
          "onDelete": "cascade",
          "onUpdate": "no action"
        }
      },
      "compositePrimaryKeys": {},
      "uniqueConstraints": {},
      "policies": {},
      "checkConstraints": {},
      "isRLSEnabled": false
    },
    "public.notifications": {
      "name": "notifications",
      "schema": "",
      "columns": {
        "id": {
          "name": "id",
          "type": "uuid",
          "primaryKey": true,
          "notNull": true,
          "default": "gen_random_uuid()"
        },
        "user_id": {
          "name": "user_id",
          "type": "uuid",
          "primaryKey": false,
          "notNull": true
        },
        "pet_id": {
          "name": "pet_id",
          "type": "uuid",
          "primaryKey": false,
          "notNull": false
        },
        "type": {
          "name": "type",
          "type": "notification_type",
          "typeSchema": "public",
          "primaryKey": false,
          "notNull": true
        },
        "title": {
          "name": "title",
          "type": "text",
          "primaryKey": false,
          "notNull": true
        },
        "message": {
          "name": "message",
          "type": "text",
          "primaryKey": false,
          "notNull": true
        },
        "scheduled_at": {
          "name": "scheduled_at",
          "type": "timestamp",
          "primaryKey": false,
          "notNull": false
        },
        "sent_at": {
          "name": "sent_at",
          "type": "timestamp",
          "primaryKey": false,
          "notNull": false
        },
        "is_read": {
          "name": "is_read",
          "type": "boolean",
          "primaryKey": false,
          "notNull": true,
          "default": false
        },
        "is_active": {
          "name": "is_active",
          "type": "boolean",
          "primaryKey": false,
          "notNull": true,
          "default": true
        },
        "metadata": {
          "name": "metadata",
          "type": "jsonb",
          "primaryKey": false,
          "notNull": false
        },
        "created_at": {
          "name": "created_at",
          "type": "timestamp",
          "primaryKey": false,
          "notNull": true,
          "default": "now()"
        },
        "updated_at": {
          "name": "updated_at",
          "type": "timestamp",
          "primaryKey": false,
          "notNull": true,
          "default": "now()"
        }
      },
      "indexes": {},
      "foreignKeys": {
        "notifications_user_id_users_id_fk": {
          "name": "notifications_user_id_users_id_fk",
          "tableFrom": "notifications",
          "tableTo": "users",
          "columnsFrom": [
            "user_id"
          ],
          "columnsTo": [
            "id"
          ],
          "onDelete": "cascade",
          "onUpdate": "no action"
        },
        "notifications_pet_id_pets_id_fk": {
          "name": "notifications_pet_id_pets_id_fk",
          "tableFrom": "notifications",
          "tableTo": "pets",
          "columnsFrom": [
            "pet_id"
          ],
          "columnsTo": [
            "id"
          ],
          "onDelete": "cascade",
          "onUpdate": "no action"
        }
      },
      "compositePrimaryKeys": {},
      "uniqueConstraints": {},
      "policies": {},
      "checkConstraints": {},
      "isRLSEnabled": false
    },
    "public.pets": {
      "name": "pets",
      "schema": "",
      "columns": {
        "id": {
          "name": "id",
          "type": "uuid",
          "primaryKey": true,
          "notNull": true,
          "default": "gen_random_uuid()"
        },
        "user_id": {
          "name": "user_id",
          "type": "uuid",
          "primaryKey": false,
          "notNull": true
        },
        "name": {
          "name": "name",
          "type": "text",
          "primaryKey": false,
          "notNull": true
        },
        "type": {
          "name": "type",
          "type": "pet_type",
          "typeSchema": "public",
          "primaryKey": false,
          "notNull": true
        },
        "breed": {
          "name": "breed",
          "type": "text",
          "primaryKey": false,
          "notNull": false
        },
        "gender": {
          "name": "gender",
          "type": "text",
          "primaryKey": false,
          "notNull": false
        },
        "birth_date": {
          "name": "birth_date",
          "type": "timestamp",
          "primaryKey": false,
          "notNull": false
        },
        "weight": {
          "name": "weight",
          "type": "numeric(5, 2)",
          "primaryKey": false,
          "notNull": false
        },
        "color": {
          "name": "color",
          "type": "text",
          "primaryKey": false,
          "notNull": false
        },
        "microchip_id": {
          "name": "microchip_id",
          "type": "text",
          "primaryKey": false,
          "notNull": false
        },
        "profile_image": {
          "name": "profile_image",
          "type": "text",
          "primaryKey": false,
          "notNull": false
        },
        "is_active": {
          "name": "is_active",
          "type": "boolean",
          "primaryKey": false,
          "notNull": true,
          "default": true
        },
        "created_at": {
          "name": "created_at",
          "type": "timestamp",
          "primaryKey": false,
          "notNull": true,
          "default": "now()"
        },
        "updated_at": {
          "name": "updated_at",
          "type": "timestamp",
          "primaryKey": false,
          "notNull": true,
          "default": "now()"
        }
      },
      "indexes": {},
      "foreignKeys": {
        "pets_user_id_users_id_fk": {
          "name": "pets_user_id_users_id_fk",
          "tableFrom": "pets",
          "tableTo": "users",
          "columnsFrom": [
            "user_id"
          ],
          "columnsTo": [
            "id"
          ],
          "onDelete": "cascade",
          "onUpdate": "no action"
        }
      },
      "compositePrimaryKeys": {},
      "uniqueConstraints": {},
      "policies": {},
      "checkConstraints": {},
      "isRLSEnabled": false
    },
    "public.users": {
      "name": "users",
      "schema": "",
      "columns": {
        "id": {
          "name": "id",
          "type": "uuid",
          "primaryKey": true,
          "notNull": true,
          "default": "gen_random_uuid()"
        },
        "clerk_id": {
          "name": "clerk_id",
          "type": "text",
          "primaryKey": false,
          "notNull": true
        },
        "email": {
          "name": "email",
          "type": "text",
          "primaryKey": false,
          "notNull": true
        },
        "first_name": {
          "name": "first_name",
          "type": "text",
          "primaryKey": false,
          "notNull": false
        },
        "last_name": {
          "name": "last_name",
          "type": "text",
          "primaryKey": false,
          "notNull": false
        },
        "profile_image": {
          "name": "profile_image",
          "type": "text",
          "primaryKey": false,
          "notNull": false
        },
        "created_at": {
          "name": "created_at",
          "type": "timestamp",
          "primaryKey": false,
          "notNull": true,
          "default": "now()"
        },
        "updated_at": {
          "name": "updated_at",
          "type": "timestamp",
          "primaryKey": false,
          "notNull": true,
          "default": "now()"
        }
      },
      "indexes": {},
      "foreignKeys": {},
      "compositePrimaryKeys": {},
      "uniqueConstraints": {
        "users_clerk_id_unique": {
          "name": "users_clerk_id_unique",
          "nullsNotDistinct": false,
          "columns": [
            "clerk_id"
          ]
        },
        "users_email_unique": {
          "name": "users_email_unique",
          "nullsNotDistinct": false,
          "columns": [
            "email"
          ]
        }
      },
      "policies": {},
      "checkConstraints": {},
      "isRLSEnabled": false
    },
    "public.vaccinations": {
      "name": "vaccinations",
      "schema": "",
      "columns": {
        "id": {
          "name": "id",
          "type": "uuid",
          "primaryKey": true,
          "notNull": true,
          "default": "gen_random_uuid()"
        },
        "pet_id": {
          "name": "pet_id",
          "type": "uuid",
          "primaryKey": false,
          "notNull": true
        },
        "vaccine_name": {
          "name": "vaccine_name",
          "type": "text",
          "primaryKey": false,
          "notNull": true
        },
        "vaccination_date": {
          "name": "vaccination_date",
          "type": "timestamp",
          "primaryKey": false,
          "notNull": true
        },
        "next_due_date": {
          "name": "next_due_date",
          "type": "timestamp",
          "primaryKey": false,
          "notNull": false
        },
        "veterinarian": {
          "name": "veterinarian",
          "type": "text",
          "primaryKey": false,
          "notNull": false
        },
        "clinic": {
          "name": "clinic",
          "type": "text",
          "primaryKey": false,
          "notNull": false
        },
        "batch_number": {
          "name": "batch_number",
          "type": "text",
          "primaryKey": false,
          "notNull": false
        },
        "notes": {
          "name": "notes",
          "type": "text",
          "primaryKey": false,
          "notNull": false
        },
        "created_at": {
          "name": "created_at",
          "type": "timestamp",
          "primaryKey": false,
          "notNull": true,
          "default": "now()"
        },
        "updated_at": {
          "name": "updated_at",
          "type": "timestamp",
          "primaryKey": false,
          "notNull": true,
          "default": "now()"
        }
      },
      "indexes": {},
      "foreignKeys": {
        "vaccinations_pet_id_pets_id_fk": {
          "name": "vaccinations_pet_id_pets_id_fk",
          "tableFrom": "vaccinations",
          "tableTo": "pets",
          "columnsFrom": [
            "pet_id"
          ],
          "columnsTo": [
            "id"
          ],
          "onDelete": "cascade",
          "onUpdate": "no action"
        }
      },
      "compositePrimaryKeys": {},
      "uniqueConstraints": {},
      "policies": {},
      "checkConstraints": {},
      "isRLSEnabled": false
    },
    "public.voice_commands": {
      "name": "voice_commands",
      "schema": "",
      "columns": {
        "id": {
          "name": "id",
          "type": "uuid",
          "primaryKey": true,
          "notNull": true,
          "default": "gen_random_uuid()"
        },
        "pet_id": {
          "name": "pet_id",
          "type": "uuid",
          "primaryKey": false,
          "notNull": true
        },
        "command": {
          "name": "command",
          "type": "text",
          "primaryKey": false,
          "notNull": true
        },
        "audio_url": {
          "name": "audio_url",
          "type": "text",
          "primaryKey": false,
          "notNull": false
        },
        "description": {
          "name": "description",
          "type": "text",
          "primaryKey": false,
          "notNull": false
        },
        "is_active": {
          "name": "is_active",
          "type": "boolean",
          "primaryKey": false,
          "notNull": true,
          "default": true
        },
        "created_at": {
          "name": "created_at",
          "type": "timestamp",
          "primaryKey": false,
          "notNull": true,
          "default": "now()"
        },
        "updated_at": {
          "name": "updated_at",
          "type": "timestamp",
          "primaryKey": false,
          "notNull": true,
          "default": "now()"
        }
      },
      "indexes": {},
      "foreignKeys": {
        "voice_commands_pet_id_pets_id_fk": {
          "name": "voice_commands_pet_id_pets_id_fk",
          "tableFrom": "voice_commands",
          "tableTo": "pets",
          "columnsFrom": [
            "pet_id"
          ],
          "columnsTo": [
            "id"
          ],
          "onDelete": "cascade",
          "onUpdate": "no action"
        }
      },
      "compositePrimaryKeys": {},
      "uniqueConstraints": {},
      "policies": {},
      "checkConstraints": {},
      "isRLSEnabled": false
    }
  },
  "enums": {
    "public.activity_type": {
      "name": "activity_type",
      "schema": "public",
      "values": [
        "walk",
        "play",
        "sleep",
        "eat",
        "exercise",
        "rest"
      ]
    },
    "public.health_status": {
      "name": "health_status",
      "schema": "public",
      "values": [
        "excellent",
        "good",
        "normal",
        "warning",
        "critical"
      ]
    },
    "public.notification_type": {
      "name": "notification_type",
      "schema": "public",
      "values": [
        "meal",
        "walk",
        "medicine",
        "checkup",
        "grooming",
        "reminder"
      ]
    },
    "public.pet_type": {
      "name": "pet_type",
      "schema": "public",
      "values": [
        "dog",
        "cat",
        "bird",
        "rabbit",
        "hamster",
        "fish",
        "reptile",
        "other"
      ]
    }
  },
  "schemas": {},
  "sequences": {},
  "roles": {},
  "policies": {},
  "views": {},
  "_meta": {
    "columns": {},
    "schemas": {},
    "tables": {}
  }
}